color4console/__init__.py
color4console/colorconsole.py
color4console/style.py
color4console-0.0.1.dist-info/LICENSE
color4console-0.0.1.dist-info/METADATA
color4console-0.0.1.dist-info/WHEEL
color4console-0.0.1.dist-info/top_level.txt
color4console-0.0.1.dist-info/RECORD
