Metadata-Version: 2.1
Name: color4console
Version: 0.0.1
Summary: color4console enables you to print colorful text without wasting time experimenting with various color combinations.
Home-page: https://github.com/Mahmud-Iftekhar-Zamil/COLOR4CONSOLE
Author: Mahmud Iftekhar Zamil
Author-email: chishty113@yahoo.com
License: UNKNOWN
Platform: UNKNOWN
Classifier: Programming Language :: Python :: 3
Classifier: License :: OSI Approved :: MIT License
Classifier: Operating System :: OS Independent
Requires-Python: >=3.6
License-File: LICENSE
